{
  "version": "5",
  "dialect": "sqlite",
  "id": "cd6cdd75-8407-4b9f-a0dc-7576c3cba97e",
  "prevId": "1e3b8b4c-af4b-4579-9676-48d1c738795d",
  "tables": {
    "player": {
      "name": "player",
      "columns": {
        "steam_id": {
          "name": "steam_id",
          "type": "text",
          "primaryKey": true,
          "notNull": true,
          "autoincrement": false
        },
        "name": {
          "name": "name",
          "type": "text",
          "primaryKey": false,
          "notNull": true,
          "autoincrement": false
        },
        "player_uid": {
          "name": "player_uid",
          "type": "text",
          "primaryKey": false,
          "notNull": true,
          "autoincrement": false
        },
        "created_at": {
          "name": "created_at",
          "type": "integer",
          "primaryKey": false,
          "notNull": true,
          "autoincrement": false,
          "default": "(strftime('%s', 'now'))"
        },
        "updated_at": {
          "name": "updated_at",
          "type": "integer",
          "primaryKey": false,
          "notNull": true,
          "autoincrement": false,
          "default": "(strftime('%s', 'now'))"
        },
        "steam_profile": {
          "name": "steam_profile",
          "type": "text",
          "primaryKey": false,
          "notNull": false,
          "autoincrement": false,
          "default": null
        }
      },
      "indexes": {},
      "foreignKeys": {},
      "compositePrimaryKeys": {},
      "uniqueConstraints": {}
    }
  },
  "enums": {},
  "_meta": {
    "schemas": {},
    "tables": {},
    "columns": {}
  }
}
